upoly/__init__.py
upoly/constants.py
upoly/models.py
upoly/polygon_plus.py
upoly/py.typed
upoly/settings.py
upoly/utility.py
upoly-0.1.34.dist-info/LICENSE
upoly-0.1.34.dist-info/WHEEL
upoly-0.1.34.dist-info/METADATA
upoly-0.1.34.dist-info/RECORD
