Metadata-Version: 2.1
Name: upoly
Version: 0.1.34
Summary: High performance asyncio REST client for polygon.io
License: AGPL
Keywords: asyncio,polygon,polygonio,python,client-python,http2
Author: Riley
Author-email: rileymshea@gmail.com
Requires-Python: >=3.8,<3.9
Classifier: Intended Audience :: Developers
Classifier: License :: Other/Proprietary License
Classifier: Operating System :: OS Independent
Classifier: Programming Language :: Python
Classifier: Programming Language :: Python :: 3
Classifier: Programming Language :: Python :: 3 :: Only
Classifier: Programming Language :: Python :: 3.8
Classifier: Topic :: Office/Business :: Financial :: Investment
Classifier: Topic :: Software Development
Classifier: Topic :: Software Development :: Libraries
Classifier: Topic :: Software Development :: Libraries :: Python Modules
Classifier: Typing :: Typed
Requires-Dist: Brotli (>=1.0.9,<2.0.0)
Requires-Dist: aiodns (>=2.0.0,<3.0.0)
Requires-Dist: aiohttp (>=3.7.4,<4.0.0)
Requires-Dist: cchardet (>=2.1.7,<3.0.0)
Requires-Dist: joblib (>=1.0.1,<2.0.0)
Requires-Dist: nest-asyncio (>=1.4.3,<2.0.0)
Requires-Dist: numpy (>=1.20.1,<2.0.0)
Requires-Dist: orjson (>=3.5.0,<4.0.0)
Requires-Dist: pandas (>=1.2.2,<2.0.0)
Requires-Dist: pandas-market-calendars (>=1.6.1,<2.0.0)
Requires-Dist: python-dotenv (>=0.15.0,<0.16.0)
